controller.v
/*****************************************************
**  Verilog-HDL Training  Lab                       **
******************************************************
**  signal controller.    FSM                       **
*****************************************************/

module control( clk, rst, count_in, count_start, g_out, y_out, r_out );
    input           clk;
    input           rst;
    input  [2:0]    count_in;
    output          count_start;
    output          g_out;
    output          y_out;
    output          r_out;

    reg             count_start;
    reg             g_out;
    reg             y_out;
    reg             r_out;

    reg    [1:0]  state, next_state;


    `define        GREEN_TIMES      3'd6
    `define        YELLOW_TIMES     3'd2
    `define        RED_TIMES        3'd4

    parameter [1:0] INIT     = 2'b00,
                    GREEN    = 2'b01,
                    YELLOW   = 2'b10,
                    RED      = 2'b11;

    always@( posedge clk ) begin
        if( rst == 1'b0 ) begin
            state <= INIT;
        end
        else begin
            state <= next_state;
        end
    end

    always@( state, count_in ) begin
        count_start <= 1'b0;
        g_out <= 1'b0;
        y_out <= 1'b0;
        r_out <= 1'b0;
        case (state)
            INIT:    begin
                count_start <= 1'b1;
                next_state <= GREEN;
            end
            GREEN: begin
                g_out <= 1'b1;
                if( count_in == `GREEN_TIMES ) begin
                    count_start <= 1'b1;
                    next_state <= YELLOW;
                end
                else begin
                    next_state <= GREEN;
                end
            end
            YELLOW: begin
                y_out <= 1'b1;
                if( count_in == `YELLOW_TIMES ) begin
                    count_start <= 1'b1;
                    next_state <= RED;
                end
                else begin
                    next_state <= YELLOW;
                end
            end
            RED: begin
                r_out <= 1'b1;
                if( count_in == `RED_TIMES ) begin
                    count_start <= 1'b1;
                    next_state <= GREEN;
                end
                else begin
                    next_state <= RED;
                end
            end    
            default: begin
                next_state <= INIT;
            end
        endcase    // end of case
    end    // end of always
endmodule

counter.v
/*****************************************************
**  Verilog-HDL Training  Lab                       **
******************************************************
**  0 to 7 counter for signal controller.           **
*****************************************************/

module count8( clk, rst, start, cout );
input clk;
input rst;
input start;
output [2:0] cout;
reg    [2:0] cout;

always @(posedge clk or negedge rst ) begin
    if( rst == 1'b0 ) begin
        cout <= 3'd0;
    end
    else if( start == 1'b1 ) begin
        cout <= 1'b1;
    end
    else begin
        cout <= cout + 3'd1;
    end
end
endmodule

testbench.v

/*****************************************************
**  Verilog-HDL Training  Lab                       **
******************************************************
**  testbench for signal controller.      			**
*****************************************************/

module testbench() ;
    reg          clock ;
    reg          reset ;

    wire [2:0]   w_count;
    reg  [2:0]   r_count;

    wire         w_start;
    reg          r_start;

    wire         w_green;
    wire         w_yellow;
    wire         w_red;

    integer seq_ct;

    count8         count( .clk(clock), .rst(reset), .start(w_start), .cout(w_count) );
    control        ctrl( .clk(clock), .rst(reset), .count_in(w_count), .count_start(w_start), .g_out(w_green), .y_out(w_yellow), .r_out(w_red) );

    initial begin
        clock = 1 ;
        forever begin
            #50 clock = ~clock ;
        end
    end

    initial begin
        $dumpfile("trace.vcd") ;
        $dumpvars ;
    end

    initial begin
		seq_ct = 0;
        reset = 1;
        @(posedge clock) ;
        reset = 0;
        @(posedge clock) ;
        reset = 1 ;
        @(posedge clock) ;

       	forever begin 
        	$display( "%0t : green= %d  yellow= %d red=%d",$time, w_green, w_yellow, w_red);
            @(posedge clock) ;
            seq_ct = seq_ct + 1;
            if( seq_ct == 37 ) begin
		    	$finish ;
            end
       	end
    end
endmodule

trace.vcd
$date
	Wed Jul 20 03:18:47 2005
$end
$version
	Icarus Verilog
$end
$timescale
	1s
$end
$scope module testbench $end
$var wire 3 ! w_count $end
$var wire 1 " w_green $end
$var wire 1 # w_red $end
$var wire 1 $ w_start $end
$var wire 1 % w_yellow $end
$var reg 1 & clock $end
$var reg 1 ' reset $end
$var reg 32 ( seq_ct $end
$scope module count $end
$var wire 1 & clk $end
$var wire 1 ' rst $end
$var wire 1 $ start $end
$var reg 3 ) cout $end
$upscope $end
$scope module ctrl $end
$var wire 1 & clk $end
$var wire 3 * count_in $end
$var wire 1 ' rst $end
$var reg 1 $ count_start $end
$var reg 1 " g_out $end
$var reg 2 + next_state $end
$var reg 1 # r_out $end
$var reg 2 , state $end
$var reg 1 % y_out $end
$upscope $end
$upscope $end
$enddefinitions $end
#0
$dumpvars
bx ,
bx +
bx *
bx )
b0 (
1'
1&
x%
x$
x#
x"
bx !
$end
#50
0&
#100
1&
0'
bx0 *
bx0 )
bx0 !
bx00 *
bx00 )
bx00 !
b0 *
b0 )
b0 !
0$
0"
0%
0#
bx0 +
b0 +
#150
0&
#200
1&
1'
bx0 ,
b0 ,
b1 *
b1 )
b1 !
1$
b1 +
#250
0&
#300
1&
b1 ,
0$
1"
#350
0&
#400
1&
b1 (
b0 *
b0 )
b0 !
b10 *
b10 )
b10 !
1"
1"
#450
0&
#500
1&
b0 (
b10 (
b11 *
b11 )
b11 !
1"
1"
#550
0&
#600
1&
b11 (
b10 *
b10 )
b10 !
b0 *
b0 )
b0 !
b100 *
b100 )
b100 !
1"
1"
#650
0&
#700
1&
b10 (
b0 (
b100 (
b101 *
b101 )
b101 !
1"
1"
#750
0&
#800
1&
b101 (
b100 *
b100 )
b100 !
b110 *
b110 )
b110 !
1"
1"
1$
b0 +
b10 +
#850
0&
#900
1&
b100 (
b110 (
b0 ,
b10 ,
b111 *
b111 )
b111 !
b101 *
b101 )
b101 !
b1 *
b1 )
b1 !
0$
0"
1%
#950
0&
#1000
1&
b111 (
b0 *
b0 )
b0 !
b10 *
b10 )
b10 !
1%
1%
1$
b11 +
#1050
0&
#1100
1&
b110 (
b100 (
b0 (
b1000 (
b11 ,
b11 *
b11 )
b11 !
b1 *
b1 )
b1 !
0$
0%
1#
#1150
0&
#1200
1&
b1001 (
b0 *
b0 )
b0 !
b10 *
b10 )
b10 !
1#
1#
#1250
0&
#1300
1&
b1000 (
b1010 (
b11 *
b11 )
b11 !
1#
1#
#1350
0&
#1400
1&
b1011 (
b10 *
b10 )
b10 !
b0 *
b0 )
b0 !
b100 *
b100 )
b100 !
1#
1#
1$
b1 +
#1450
0&
#1500
1&
b1010 (
b1000 (
b1100 (
b1 ,
b101 *
b101 )
b101 !
b1 *
b1 )
b1 !
0$
0#
1"
#1550
0&
#1600
1&
b1101 (
b0 *
b0 )
b0 !
b10 *
b10 )
b10 !
1"
1"
#1650
0&
#1700
1&
b1100 (
b1110 (
b11 *
b11 )
b11 !
1"
1"
#1750
0&
#1800
1&
b1111 (
b10 *
b10 )
b10 !
b0 *
b0 )
b0 !
b100 *
b100 )
b100 !
1"
1"
#1850
0&
#1900
1&
b1110 (
b1100 (
b1000 (
b0 (
b10000 (
b101 *
b101 )
b101 !
1"
1"
#1950
0&
#2000
1&
b10001 (
b100 *
b100 )
b100 !
b110 *
b110 )
b110 !
1"
1"
1$
b0 +
b10 +
#2050
0&
#2100
1&
b10000 (
b10010 (
b0 ,
b10 ,
b111 *
b111 )
b111 !
b101 *
b101 )
b101 !
b1 *
b1 )
b1 !
0$
0"
1%
#2150
0&
#2200
1&
b10011 (
b0 *
b0 )
b0 !
b10 *
b10 )
b10 !
1%
1%
1$
b11 +
#2250
0&
#2300
1&
b10010 (
b10000 (
b10100 (
b11 ,
b11 *
b11 )
b11 !
b1 *
b1 )
b1 !
0$
0%
1#
#2350
0&
#2400
1&
b10101 (
b0 *
b0 )
b0 !
b10 *
b10 )
b10 !
1#
1#
#2450
0&
#2500
1&
b10100 (
b10110 (
b11 *
b11 )
b11 !
1#
1#
#2550
0&
#2600
1&
b10111 (
b10 *
b10 )
b10 !
b0 *
b0 )
b0 !
b100 *
b100 )
b100 !
1#
1#
1$
b1 +
#2650
0&
#2700
1&
b10110 (
b10100 (
b10000 (
b11000 (
b1 ,
b101 *
b101 )
b101 !
b1 *
b1 )
b1 !
0$
0#
1"
#2750
0&
#2800
1&
b11001 (
b0 *
b0 )
b0 !
b10 *
b10 )
b10 !
1"
1"
#2850
0&
#2900
1&
b11000 (
b11010 (
b11 *
b11 )
b11 !
1"
1"
#2950
0&
#3000
1&
b11011 (
b10 *
b10 )
b10 !
b0 *
b0 )
b0 !
b100 *
b100 )
b100 !
1"
1"
#3050
0&
#3100
1&
b11010 (
b11000 (
b11100 (
b101 *
b101 )
b101 !
1"
1"
#3150
0&
#3200
1&
b11101 (
b100 *
b100 )
b100 !
b110 *
b110 )
b110 !
1"
1"
1$
b0 +
b10 +
#3250
0&
#3300
1&
b11100 (
b11110 (
b0 ,
b10 ,
b111 *
b111 )
b111 !
b101 *
b101 )
b101 !
b1 *
b1 )
b1 !
0$
0"
1%
#3350
0&
#3400
1&
b11111 (
b0 *
b0 )
b0 !
b10 *
b10 )
b10 !
1%
1%
1$
b11 +
#3450
0&
#3500
1&
b11110 (
b11100 (
b11000 (
b10000 (
b0 (
b100000 (
b11 ,
b11 *
b11 )
b11 !
b1 *
b1 )
b1 !
0$
0%
1#
#3550
0&
#3600
1&
b100001 (
b0 *
b0 )
b0 !
b10 *
b10 )
b10 !
1#
1#
#3650
0&
#3700
1&
b100000 (
b100010 (
b11 *
b11 )
b11 !
1#
1#
#3750
0&
#3800
1&
b100011 (
b10 *
b10 )
b10 !
b0 *
b0 )
b0 !
b100 *
b100 )
b100 !
1#
1#
1$
b1 +
#3850
0&
#3900
1&
b100010 (
b100000 (
b100100 (
b1 ,
b101 *
b101 )
b101 !
b1 *
b1 )
b1 !
0$
0#
1"
#3950
0&
#4000
1&
b100101 (
